setup.cfg
setup.py
src/twocaptcha/__init__.py
src/twocaptcha/twocaptcha.py
twocaptcha_wrapper.egg-info/PKG-INFO
twocaptcha_wrapper.egg-info/SOURCES.txt
twocaptcha_wrapper.egg-info/dependency_links.txt
twocaptcha_wrapper.egg-info/requires.txt
twocaptcha_wrapper.egg-info/top_level.txt