Metadata-Version: 1.1
Name: twocaptcha-wrapper
Version: 0.1.2
Summary: 2Captcha Wrapper - ReCaptchaV2 token based
Home-page: https://github.com/tiagocardosoweb/2captcha-wrapper
Author: Tiago Cardoso
Author-email: tiagocardosoweb@gmail.com
License: UNKNOWN
Download-URL: https://github.com/tiagocardosoweb/2captcha-wrapper/archive/0.1.2.tar.gz
Keywords: 2captcha,captcha,Image Recognition,reRecaptcha,reRecaptcha V2
Platform: UNKNOWN
Classifier: Topic :: Scientific/Engineering :: Image Recognition
